acsecure/__init__.py
acsecure/middleware.py
django_acsecure-0.1.3.dist-info/LICENSE
django_acsecure-0.1.3.dist-info/METADATA
django_acsecure-0.1.3.dist-info/WHEEL
django_acsecure-0.1.3.dist-info/top_level.txt
django_acsecure-0.1.3.dist-info/RECORD
