Metadata-Version: 2.1
Name: django-acsecure
Version: 0.1.3
Summary: Access Secure Django Middleware
Home-page: https://github.com/TrentaIcedCoffee/access-secure
Author: Xin Jin
Author-email: opposcript@gmail.com
License: MIT
Keywords: django,log,anti-spam
Platform: OS Independent
Classifier: Programming Language :: Python :: 3
Classifier: License :: OSI Approved :: MIT License
Classifier: Operating System :: OS Independent
Requires-Python: >=3.5
Requires-Dist: asgiref (==3.2.3)
Requires-Dist: certifi (==2019.11.28)
Requires-Dist: chardet (==3.0.4)
Requires-Dist: Django (==3.0.3)
Requires-Dist: idna (==2.8)
Requires-Dist: pytz (==2019.3)
Requires-Dist: requests (==2.22.0)
Requires-Dist: sqlparse (==0.3.0)
Requires-Dist: urllib3 (==1.25.8)
